pypx/__init__.py
pypx/base.py
pypx/do.py
pypx/echo.py
pypx/find.py
pypx/listen.py
pypx/move.py
pypx/nxstatus.py
pypx/pfstorage.py
pypx/push.py
pypx/register.py
pypx/repack.py
pypx/report.py
pypx/smdb.py
pypx/status.py
pypx/utils.py
pypx-3.12.6.data/scripts/pfstorage
pypx-3.12.6.data/scripts/px-do
pypx-3.12.6.data/scripts/px-echo
pypx-3.12.6.data/scripts/px-find
pypx-3.12.6.data/scripts/px-listen
pypx-3.12.6.data/scripts/px-move
pypx-3.12.6.data/scripts/px-push
pypx-3.12.6.data/scripts/px-register
pypx-3.12.6.data/scripts/px-repack
pypx-3.12.6.data/scripts/px-report
pypx-3.12.6.data/scripts/px-smdb
pypx-3.12.6.data/scripts/px-status
pypx-3.12.6.data/scripts/storescp.sh
pypx-3.12.6.dist-info/METADATA
pypx-3.12.6.dist-info/WHEEL
pypx-3.12.6.dist-info/top_level.txt
pypx-3.12.6.dist-info/RECORD
