Metadata-Version: 2.1
Name: pypx
Version: 3.12.6
Summary: PACS/ChRIS core tools and utils
Home-page: http://github.com/FNNDSC/pypx
Author: FNNDSC Developers
Author-email: dev@babyMRI.org
License: MIT
Requires-Python: >= 3.8
Requires-Dist: pudb
Requires-Dist: terminaltables
Requires-Dist: python-dateutil
Requires-Dist: pydicom
Requires-Dist: pfmisc
Requires-Dist: dask
Requires-Dist: retry
Requires-Dist: psutil
Requires-Dist: python-swiftclient
Requires-Dist: pfstate
Requires-Dist: webob
Requires-Dist: seahash
Requires-Dist: aiohttp
Requires-Dist: python-chrisclient
